<?xml version="1.0" encoding="UTF-8"?>

<!-- generated on Tue Feb 18 13:32:01 2014 by SUMO sumo Version 0.19.0
<?xml version="1.0" encoding="UTF-8"?>

<configuration xmlns:xsi="http://www.w3.org/2001/XMLSchema-instance" xsi:noNamespaceSchemaLocation="http://sumo-sim.org/xsd/sumoConfiguration.xsd">

    <input>
        <net-file value="data/map.net.xml"/>
        <route-files value="data/map.rou.xml"/>
    </input>

    <output>
        <tripinfo-output value="data/maptripinfo.out.xml"/>
        <save-state.prefix value="data/state"/>
    </output>

    <time>
        <begin value="25200"/>
        <end value="26100"/>
    </time>

    <processing>
        <route-steps value="200"/>
        <scale value="0.1"/>
        <time-to-teleport value="300"/>
        <lanechange.allow-swap value="true"/>
    </processing>

    <report>
        <verbose value="true"/>
        <no-warnings value="false"/>
        <no-step-log value="true"/>
    </report>

    <routing>
        <device.rerouting.probability value="1"/>
    </routing>

</configuration>
-->

<tripinfos>
    <tripinfo id="160035_160035_421" depart="25200.00" departLane="8225127_0" departPos="5.10" departSpeed="0.00" departDelay="0.00" arrival="25206.00" arrivalLane="8225127_0" arrivalPos="38.87" arrivalSpeed="12.16" duration="6.00" routeLength="33.77" waitSteps="0" rerouteNo="1" devices="tripinfo_160035_160035_421 routing_160035_160035_421" vType="DEFAULT_VEHTYPE" vaporized=""/>
    <tripinfo id="146065_146065_416" depart="25200.00" departLane="185767959#0_0" departPos="5.10" departSpeed="0.00" departDelay="0.00" arrival="25211.00" arrivalLane="9207798_1" arrivalPos="76.33" arrivalSpeed="17.78" duration="11.00" routeLength="90.29" waitSteps="0" rerouteNo="1" devices="tripinfo_146065_146065_416 routing_146065_146065_416" vType="DEFAULT_VEHTYPE" vaporized=""/>
    <tripinfo id="135816_135816_411" depart="25200.00" departLane="23471158#6_0" departPos="5.10" departSpeed="0.00" departDelay="0.00" arrival="25218.00" arrivalLane="23471158#9_0" arrivalPos="213.75" arrivalSpeed="26.77" duration="18.00" routeLength="308.43" waitSteps="0" rerouteNo="1" devices="tripinfo_135816_135816_411 routing_135816_135816_411" vType="DEFAULT_VEHTYPE" vaporized=""/>
    <tripinfo id="100948_100948_396" depart="25200.00" departLane="154743410#2_0" departPos="5.10" departSpeed="0.00" departDelay="0.00" arrival="25220.00" arrivalLane="9207798_1" arrivalPos="76.33" arrivalSpeed="16.50" duration="20.00" routeLength="167.61" waitSteps="0" rerouteNo="1" devices="tripinfo_100948_100948_396 routing_100948_100948_396" vType="DEFAULT_VEHTYPE" vaporized=""/>
    <tripinfo id="95769_95769_394" depart="25200.00" departLane="154743410#1_0" departPos="5.10" departSpeed="0.00" departDelay="0.00" arrival="25228.00" arrivalLane="9207798_1" arrivalPos="76.33" arrivalSpeed="19.37" duration="28.00" routeLength="298.40" waitSteps="0" rerouteNo="1" devices="tripinfo_95769_95769_394 routing_95769_95769_394" vType="DEFAULT_VEHTYPE" vaporized=""/>
    <tripinfo id="80988_80988_388" depart="25207.00" departLane="154743410#2_0" departPos="5.10" departSpeed="0.00" departDelay="7.00" arrival="25232.00" arrivalLane="9207798_1" arrivalPos="76.33" arrivalSpeed="20.95" duration="25.00" routeLength="167.61" waitSteps="0" rerouteNo="1" devices="tripinfo_80988_80988_388 routing_80988_80988_388" vType="DEFAULT_VEHTYPE" vaporized=""/>
    <tripinfo id="113896_113896_402" depart="25200.00" departLane="4380937#0_0" departPos="5.10" departSpeed="0.00" departDelay="0.00" arrival="25243.00" arrivalLane="145575263_1" arrivalPos="260.32" arrivalSpeed="13.22" duration="43.00" routeLength="481.40" waitSteps="0" rerouteNo="1" devices="tripinfo_113896_113896_402 routing_113896_113896_402" vType="DEFAULT_VEHTYPE" vaporized=""/>
    <tripinfo id="125000_125000_406" depart="25206.00" departLane="185767958#1_0" departPos="5.10" departSpeed="0.00" departDelay="6.00" arrival="25255.00" arrivalLane="23471158#9_0" arrivalPos="213.75" arrivalSpeed="26.60" duration="49.00" routeLength="782.30" waitSteps="0" rerouteNo="1" devices="tripinfo_125000_125000_406 routing_125000_125000_406" vType="DEFAULT_VEHTYPE" vaporized=""/>
    <tripinfo id="128656_128656_408" depart="25200.00" departLane="36454807#3-AddedOnRampEdge_0" departPos="5.10" departSpeed="0.00" departDelay="0.00" arrival="25256.00" arrivalLane="129833339#1_0" arrivalPos="41.68" arrivalSpeed="13.00" duration="56.00" routeLength="728.25" waitSteps="0" rerouteNo="1" devices="tripinfo_128656_128656_408 routing_128656_128656_408" vType="DEFAULT_VEHTYPE" vaporized=""/>
    <tripinfo id="128669_128669_408" depart="25201.00" departLane="151057637#2_0" departPos="5.10" departSpeed="0.00" departDelay="0.00" arrival="25257.00" arrivalLane="23471158#9_0" arrivalPos="213.75" arrivalSpeed="27.41" duration="56.00" routeLength="904.86" waitSteps="0" rerouteNo="1" devices="tripinfo_128669_128669_408 routing_128669_128669_408" vType="DEFAULT_VEHTYPE" vaporized=""/>
    <tripinfo id="149028_149028_417" depart="25233.00" departLane="-200671461_0" departPos="5.10" departSpeed="0.00" departDelay="0.00" arrival="25261.00" arrivalLane="-22873531#1_0" arrivalPos="92.66" arrivalSpeed="13.20" duration="28.00" routeLength="244.92" waitSteps="0" rerouteNo="1" devices="tripinfo_149028_149028_417 routing_149028_149028_417" vType="DEFAULT_VEHTYPE" vaporized=""/>
    <tripinfo id="146668_146668_416" depart="25210.00" departLane="31694310#0_0" departPos="5.10" departSpeed="0.00" departDelay="0.00" arrival="25285.00" arrivalLane="37866521#1_0" arrivalPos="52.00" arrivalSpeed="12.85" duration="75.00" routeLength="1026.54" waitSteps="0" rerouteNo="1" devices="tripinfo_146668_146668_416 routing_146668_146668_416" vType="DEFAULT_VEHTYPE" vaporized=""/>
    <tripinfo id="150882_150882_418" depart="25226.00" departLane="31694310#0_0" departPos="5.10" departSpeed="0.00" departDelay="0.00" arrival="25303.00" arrivalLane="37866521#1_0" arrivalPos="52.00" arrivalSpeed="13.06" duration="77.00" routeLength="1026.54" waitSteps="0" rerouteNo="1" devices="tripinfo_150882_150882_418 routing_150882_150882_418" vType="DEFAULT_VEHTYPE" vaporized=""/>
    <tripinfo id="139768_139768_413" depart="25218.00" departLane="28557537#1_0" departPos="5.10" departSpeed="0.00" departDelay="0.00" arrival="25322.00" arrivalLane="145575263_1" arrivalPos="260.32" arrivalSpeed="13.68" duration="104.00" routeLength="911.63" waitSteps="31" rerouteNo="1" devices="tripinfo_139768_139768_413 routing_139768_139768_413" vType="DEFAULT_VEHTYPE" vaporized=""/>
    <tripinfo id="162274_162274_421" depart="25273.00" departLane="151057637#2_0" departPos="5.10" departSpeed="0.00" departDelay="0.00" arrival="25322.00" arrivalLane="23471158#9_0" arrivalPos="213.75" arrivalSpeed="27.49" duration="49.00" routeLength="917.61" waitSteps="0" rerouteNo="1" devices="tripinfo_162274_162274_421 routing_162274_162274_421" vType="DEFAULT_VEHTYPE" vaporized=""/>
    <tripinfo id="147926_147926_416" depart="25262.00" departLane="31694310#0_0" departPos="5.10" departSpeed="0.00" departDelay="0.00" arrival="25327.00" arrivalLane="154755102#0_0" arrivalPos="142.19" arrivalSpeed="13.37" duration="65.00" routeLength="746.39" waitSteps="0" rerouteNo="1" devices="tripinfo_147926_147926_416 routing_147926_147926_416" vType="DEFAULT_VEHTYPE" vaporized=""/>
    <tripinfo id="121884_121884_406" depart="25205.00" departLane="154743410#2_0" departPos="5.10" departSpeed="0.00" departDelay="5.00" arrival="25328.00" arrivalLane="145575263_1" arrivalPos="260.32" arrivalSpeed="13.59" duration="123.00" routeLength="1261.67" waitSteps="10" rerouteNo="1" devices="tripinfo_121884_121884_406 routing_121884_121884_406" vType="DEFAULT_VEHTYPE" vaporized=""/>
    <tripinfo id="108411_108411_400" depart="25203.00" departLane="154743410#2_0" departPos="5.10" departSpeed="0.00" departDelay="3.00" arrival="25331.00" arrivalLane="145575263_1" arrivalPos="260.32" arrivalSpeed="13.08" duration="128.00" routeLength="1261.67" waitSteps="14" rerouteNo="1" devices="tripinfo_108411_108411_400 routing_108411_108411_400" vType="DEFAULT_VEHTYPE" vaporized=""/>
    <tripinfo id="148790_148790_417" depart="25291.00" departLane="4400203#0_0" departPos="5.10" departSpeed="0.00" departDelay="0.00" arrival="25333.00" arrivalLane="9207798_1" arrivalPos="76.33" arrivalSpeed="17.33" duration="42.00" routeLength="447.77" waitSteps="0" rerouteNo="1" devices="tripinfo_148790_148790_417 routing_148790_148790_417" vType="DEFAULT_VEHTYPE" vaporized=""/>
    <tripinfo id="134405_134405_411" depart="25256.00" departLane="151057637#2_0" departPos="5.10" departSpeed="0.00" departDelay="0.00" arrival="25342.00" arrivalLane="2837877_0" arrivalPos="210.13" arrivalSpeed="7.72" duration="86.00" routeLength="842.70" waitSteps="0" rerouteNo="1" devices="tripinfo_134405_134405_411 routing_134405_134405_411" vType="DEFAULT_VEHTYPE" vaporized=""/>
    <tripinfo id="131294_131294_410" depart="25267.00" departLane="151057637#2_0" departPos="5.10" departSpeed="0.00" departDelay="0.00" arrival="25347.00" arrivalLane="2837877_0" arrivalPos="210.13" arrivalSpeed="7.16" duration="80.00" routeLength="842.70" waitSteps="0" rerouteNo="1" devices="tripinfo_131294_131294_410 routing_131294_131294_410" vType="DEFAULT_VEHTYPE" vaporized=""/>
    <tripinfo id="141886_141886_415" depart="25304.00" departLane="154755085#0_0" departPos="5.10" departSpeed="0.00" departDelay="0.00" arrival="25362.00" arrivalLane="122989592#2_1" arrivalPos="74.34" arrivalSpeed="7.11" duration="58.00" routeLength="523.53" waitSteps="0" rerouteNo="1" devices="tripinfo_141886_141886_415 routing_141886_141886_415" vType="DEFAULT_VEHTYPE" vaporized=""/>
    <tripinfo id="105374_105374_398" depart="25200.00" departLane="185767958#1_0" departPos="5.10" departSpeed="0.00" departDelay="0.00" arrival="25362.00" arrivalLane="4390557#1_0" arrivalPos="163.47" arrivalSpeed="7.24" duration="162.00" routeLength="1373.49" waitSteps="22" rerouteNo="1" devices="tripinfo_105374_105374_398 routing_105374_105374_398" vType="DEFAULT_VEHTYPE" vaporized=""/>
    <tripinfo id="117439_117439_404" depart="25203.00" departLane="185767958#1_0" departPos="5.10" departSpeed="0.00" departDelay="3.00" arrival="25362.00" arrivalLane="51534019#0_0" arrivalPos="140.71" arrivalSpeed="13.72" duration="159.00" routeLength="1757.48" waitSteps="44" rerouteNo="1" devices="tripinfo_117439_117439_404 routing_117439_117439_404" vType="DEFAULT_VEHTYPE" vaporized=""/>
    <tripinfo id="137304_137304_412" depart="25343.00" departLane="4400448_0" departPos="5.10" departSpeed="0.00" departDelay="0.00" arrival="25370.00" arrivalLane="4400448_0" arrivalPos="197.56" arrivalSpeed="7.91" duration="27.00" routeLength="192.46" waitSteps="0" rerouteNo="1" devices="tripinfo_137304_137304_412 routing_137304_137304_412" vType="DEFAULT_VEHTYPE" vaporized=""/>
    <tripinfo id="160988_160988_421" depart="25329.00" departLane="210039165#1_0" departPos="5.10" departSpeed="0.00" departDelay="0.00" arrival="25380.00" arrivalLane="200671461_0" arrivalPos="64.70" arrivalSpeed="13.08" duration="51.00" routeLength="388.50" waitSteps="0" rerouteNo="1" devices="tripinfo_160988_160988_421 routing_160988_160988_421" vType="DEFAULT_VEHTYPE" vaporized=""/>
    <tripinfo id="167411_167411_425" depart="25241.00" departLane="9207800#0_0" departPos="5.10" departSpeed="0.00" departDelay="0.00" arrival="25383.00" arrivalLane="23493260#7_1" arrivalPos="59.96" arrivalSpeed="13.38" duration="142.00" routeLength="1776.42" waitSteps="11" rerouteNo="1" devices="tripinfo_167411_167411_425 routing_167411_167411_425" vType="DEFAULT_VEHTYPE" vaporized=""/>
    <tripinfo id="91681_91681_392" depart="25209.00" departLane="185767958#1_0" departPos="5.10" departSpeed="0.00" departDelay="9.00" arrival="25388.00" arrivalLane="69366483_0" arrivalPos="108.40" arrivalSpeed="7.66" duration="179.00" routeLength="1717.77" waitSteps="38" rerouteNo="1" devices="tripinfo_91681_91681_392 routing_91681_91681_392" vType="DEFAULT_VEHTYPE" vaporized=""/>
    <tripinfo id="166399_166399_424" depart="25372.00" departLane="180723491_0" departPos="5.10" departSpeed="0.00" departDelay="0.00" arrival="25389.00" arrivalLane="154743411#1-AddedOnRampEdge_1" arrivalPos="103.60" arrivalSpeed="27.21" duration="17.00" routeLength="262.39" waitSteps="0" rerouteNo="1" devices="tripinfo_166399_166399_424 routing_166399_166399_424" vType="DEFAULT_VEHTYPE" vaporized=""/>
    <tripinfo id="132570_132570_410" depart="25222.00" departLane="151057637#2_0" departPos="5.10" departSpeed="0.00" departDelay="0.00" arrival="25390.00" arrivalLane="-144935692#1_0" arrivalPos="107.95" arrivalSpeed="13.31" duration="168.00" routeLength="1168.72" waitSteps="69" rerouteNo="1" devices="tripinfo_132570_132570_410 routing_132570_132570_410" vType="DEFAULT_VEHTYPE" vaporized=""/>
    <tripinfo id="142023_142023_415" depart="25377.00" departLane="-175607927#0_0" departPos="5.10" departSpeed="0.00" departDelay="0.00" arrival="25391.00" arrivalLane="-175607927#0_0" arrivalPos="142.78" arrivalSpeed="12.70" duration="14.00" routeLength="137.68" waitSteps="0" rerouteNo="1" devices="tripinfo_142023_142023_415 routing_142023_142023_415" vType="DEFAULT_VEHTYPE" vaporized=""/>
    <tripinfo id="159074_159074_421" depart="25296.00" departLane="31694310#0_0" departPos="5.10" departSpeed="0.00" departDelay="0.00" arrival="25392.00" arrivalLane="23493260#7_0" arrivalPos="59.96" arrivalSpeed="12.74" duration="96.00" routeLength="1181.88" waitSteps="0" rerouteNo="1" devices="tripinfo_159074_159074_421 routing_159074_159074_421" vType="DEFAULT_VEHTYPE" vaporized=""/>
    <tripinfo id="162132_162132_421" depart="25247.00" departLane="151057637#2_0" departPos="5.10" departSpeed="0.00" departDelay="0.00" arrival="25402.00" arrivalLane="145575263_1" arrivalPos="260.32" arrivalSpeed="13.34" duration="155.00" routeLength="1287.85" waitSteps="39" rerouteNo="1" devices="tripinfo_162132_162132_421 routing_162132_162132_421" vType="DEFAULT_VEHTYPE" vaporized=""/>
    <tripinfo id="151883_151883_419" depart="25348.00" departLane="28557537#1_0" departPos="5.10" departSpeed="0.00" departDelay="0.00" arrival="25404.00" arrivalLane="28542995#0_0" arrivalPos="102.48" arrivalSpeed="13.15" duration="56.00" routeLength="1057.83" waitSteps="0" rerouteNo="1" devices="tripinfo_151883_151883_419 routing_151883_151883_419" vType="DEFAULT_VEHTYPE" vaporized=""/>
    <tripinfo id="156975_156975_421" depart="25315.00" departLane="151057637#2_0" departPos="5.10" departSpeed="0.00" departDelay="0.00" arrival="25404.00" arrivalLane="23471158#9_0" arrivalPos="213.75" arrivalSpeed="27.77" duration="89.00" routeLength="917.61" waitSteps="23" rerouteNo="1" devices="tripinfo_156975_156975_421 routing_156975_156975_421" vType="DEFAULT_VEHTYPE" vaporized=""/>
    <tripinfo id="152647_152647_419" depart="25309.00" departLane="37331980#0_0" departPos="5.10" departSpeed="0.00" departDelay="0.00" arrival="25410.00" arrivalLane="2832027#0_0" arrivalPos="102.82" arrivalSpeed="7.18" duration="101.00" routeLength="869.88" waitSteps="10" rerouteNo="1" devices="tripinfo_152647_152647_419 routing_152647_152647_419" vType="DEFAULT_VEHTYPE" vaporized=""/>
    <tripinfo id="147136_147136_416" depart="25285.00" departLane="165515969#0_0" departPos="5.10" departSpeed="0.00" departDelay="0.00" arrival="25419.00" arrivalLane="166234884_0" arrivalPos="109.97" arrivalSpeed="7.43" duration="134.00" routeLength="951.91" waitSteps="43" rerouteNo="1" devices="tripinfo_147136_147136_416 routing_147136_147136_416" vType="DEFAULT_VEHTYPE" vaporized=""/>
    <tripinfo id="152254_152254_419" depart="25394.00" departLane="-175607927#0_0" departPos="5.10" departSpeed="0.00" departDelay="0.00" arrival="25422.00" arrivalLane="4400305_1" arrivalPos="163.40" arrivalSpeed="12.70" duration="28.00" routeLength="301.08" waitSteps="0" rerouteNo="1" devices="tripinfo_152254_152254_419 routing_152254_152254_419" vType="DEFAULT_VEHTYPE" vaporized=""/>
    <tripinfo id="158101_158101_421" depart="25407.00" departLane="2829323#0_0" departPos="5.10" departSpeed="0.00" departDelay="0.00" arrival="25432.00" arrivalLane="23471158#9_0" arrivalPos="213.75" arrivalSpeed="27.72" duration="25.00" routeLength="305.22" waitSteps="0" rerouteNo="1" devices="tripinfo_158101_158101_421 routing_158101_158101_421" vType="DEFAULT_VEHTYPE" vaporized=""/>
    <tripinfo id="166839_166839_424" depart="25355.00" departLane="31694310#0_0" departPos="5.10" departSpeed="0.00" departDelay="0.00" arrival="25433.00" arrivalLane="37866521#1_0" arrivalPos="52.00" arrivalSpeed="13.38" duration="78.00" routeLength="1026.54" waitSteps="0" rerouteNo="1" devices="tripinfo_166839_166839_424 routing_166839_166839_424" vType="DEFAULT_VEHTYPE" vaporized=""/>
    <tripinfo id="143734_143734_416" depart="25336.00" departLane="28557537#1_0" departPos="5.10" departSpeed="0.00" departDelay="0.00" arrival="25437.00" arrivalLane="145575263_1" arrivalPos="260.32" arrivalSpeed="13.23" duration="101.00" routeLength="1113.97" waitSteps="0" rerouteNo="1" devices="tripinfo_143734_143734_416 routing_143734_143734_416" vType="DEFAULT_VEHTYPE" vaporized=""/>
    <tripinfo id="154290_154290_420" depart="25360.00" departLane="9207800#0_0" departPos="5.10" departSpeed="0.00" departDelay="0.00" arrival="25437.00" arrivalLane="48405468#0_0" arrivalPos="147.93" arrivalSpeed="8.25" duration="77.00" routeLength="796.73" waitSteps="0" rerouteNo="1" devices="tripinfo_154290_154290_420 routing_154290_154290_420" vType="DEFAULT_VEHTYPE" vaporized=""/>
    <tripinfo id="160282_160282_421" depart="25320.00" departLane="53212168#0_0" departPos="5.10" departSpeed="0.00" departDelay="0.00" arrival="25471.00" arrivalLane="85470309#4_0" arrivalPos="208.83" arrivalSpeed="13.76" duration="151.00" routeLength="1621.82" waitSteps="0" rerouteNo="1" devices="tripinfo_160282_160282_421 routing_160282_160282_421" vType="DEFAULT_VEHTYPE" vaporized=""/>
    <tripinfo id="151413_151413_418" depart="25412.00" departLane="8225102_0" departPos="5.10" departSpeed="0.00" departDelay="0.00" arrival="25474.00" arrivalLane="85470309#4_0" arrivalPos="208.83" arrivalSpeed="13.63" duration="62.00" routeLength="531.09" waitSteps="0" rerouteNo="1" devices="tripinfo_151413_151413_418 routing_151413_151413_418" vType="DEFAULT_VEHTYPE" vaporized=""/>
    <tripinfo id="174896_174896_427" depart="25402.00" departLane="31694310#0_0" departPos="5.10" departSpeed="0.00" departDelay="1.00" arrival="25477.00" arrivalLane="37866521#1_0" arrivalPos="52.00" arrivalSpeed="13.20" duration="75.00" routeLength="1026.54" waitSteps="0" rerouteNo="1" devices="tripinfo_174896_174896_427 routing_174896_174896_427" vType="DEFAULT_VEHTYPE" vaporized=""/>
    <tripinfo id="144164_144164_416" depart="25465.00" departLane="110967367#0_0" departPos="5.10" departSpeed="0.00" departDelay="0.00" arrival="25478.00" arrivalLane="110967367#0_0" arrivalPos="154.26" arrivalSpeed="25.29" duration="13.00" routeLength="149.16" waitSteps="0" rerouteNo="1" devices="tripinfo_144164_144164_416 routing_144164_144164_416" vType="DEFAULT_VEHTYPE" vaporized=""/>
    <tripinfo id="162625_162625_422" depart="25381.00" departLane="37331980#0_0" departPos="5.10" departSpeed="0.00" departDelay="0.00" arrival="25478.00" arrivalLane="23471158#9_0" arrivalPos="213.75" arrivalSpeed="26.54" duration="97.00" routeLength="952.35" waitSteps="19" rerouteNo="1" devices="tripinfo_162625_162625_422 routing_162625_162625_422" vType="DEFAULT_VEHTYPE" vaporized=""/>
    <tripinfo id="176127_176127_428" depart="25453.00" departLane="31694310#0_0" departPos="5.10" departSpeed="0.00" departDelay="0.00" arrival="25488.00" arrivalLane="8225124#0_0" arrivalPos="91.75" arrivalSpeed="12.60" duration="35.00" routeLength="455.19" waitSteps="0" rerouteNo="1" devices="tripinfo_176127_176127_428 routing_176127_176127_428" vType="DEFAULT_VEHTYPE" vaporized=""/>
    <tripinfo id="151280_151280_418" depart="25421.00" departLane="37331980#0_0" departPos="5.10" departSpeed="0.00" departDelay="0.00" arrival="25493.00" arrivalLane="23471158#9_0" arrivalPos="213.75" arrivalSpeed="27.18" duration="72.00" routeLength="952.35" waitSteps="0" rerouteNo="1" devices="tripinfo_151280_151280_418 routing_151280_151280_418" vType="DEFAULT_VEHTYPE" vaporized=""/>
    <tripinfo id="144131_144131_416" depart="25459.00" departLane="8225144#1_0" departPos="5.10" departSpeed="0.00" departDelay="0.00" arrival="25507.00" arrivalLane="-69366482#2_0" arrivalPos="64.24" arrivalSpeed="13.56" duration="48.00" routeLength="442.33" waitSteps="0" rerouteNo="1" devices="tripinfo_144131_144131_416 routing_144131_144131_416" vType="DEFAULT_VEHTYPE" vaporized=""/>
    <tripinfo id="167918_167918_425" depart="25388.00" departLane="154755085#0_0" departPos="5.10" departSpeed="0.00" departDelay="0.00" arrival="25511.00" arrivalLane="150039002#2_0" arrivalPos="261.12" arrivalSpeed="13.60" duration="123.00" routeLength="1510.78" waitSteps="0" rerouteNo="1" devices="tripinfo_167918_167918_425 routing_167918_167918_425" vType="DEFAULT_VEHTYPE" vaporized=""/>
    <tripinfo id="140110_140110_414" depart="25366.00" departLane="28557537#1_0" departPos="5.10" departSpeed="0.00" departDelay="0.00" arrival="25518.00" arrivalLane="145575263_1" arrivalPos="260.32" arrivalSpeed="12.91" duration="152.00" routeLength="1113.97" waitSteps="43" rerouteNo="1" devices="tripinfo_140110_140110_414 routing_140110_140110_414" vType="DEFAULT_VEHTYPE" vaporized=""/>
    <tripinfo id="150772_150772_418" depart="25507.00" departLane="151057637#2_0" departPos="5.10" departSpeed="0.00" departDelay="0.00" arrival="25521.00" arrivalLane="9207798_0" arrivalPos="76.33" arrivalSpeed="27.27" duration="14.00" routeLength="193.79" waitSteps="0" rerouteNo="1" devices="tripinfo_150772_150772_418 routing_150772_150772_418" vType="DEFAULT_VEHTYPE" vaporized=""/>
    <tripinfo id="181057_181057_431" depart="25491.00" departLane="31694310#0_0" departPos="5.10" departSpeed="0.00" departDelay="0.00" arrival="25526.00" arrivalLane="8225124#0_0" arrivalPos="91.75" arrivalSpeed="13.42" duration="35.00" routeLength="455.19" waitSteps="0" rerouteNo="1" devices="tripinfo_181057_181057_431 routing_181057_181057_431" vType="DEFAULT_VEHTYPE" vaporized=""/>
    <tripinfo id="159059_159059_421" depart="25427.00" departLane="37331980#0_0" departPos="5.10" departSpeed="0.00" departDelay="0.00" arrival="25534.00" arrivalLane="23800191#3_0" arrivalPos="128.87" arrivalSpeed="12.63" duration="107.00" routeLength="1333.06" waitSteps="0" rerouteNo="1" devices="tripinfo_159059_159059_421 routing_159059_159059_421" vType="DEFAULT_VEHTYPE" vaporized=""/>
    <tripinfo id="170659_170659_426" depart="25514.00" departLane="165515969#0_0" departPos="5.10" departSpeed="0.00" departDelay="0.00" arrival="25538.00" arrivalLane="160971552_0" arrivalPos="96.86" arrivalSpeed="27.70" duration="24.00" routeLength="464.57" waitSteps="0" rerouteNo="1" devices="tripinfo_170659_170659_426 routing_170659_170659_426" vType="DEFAULT_VEHTYPE" vaporized=""/>
    <tripinfo id="143559_143559_415" depart="25447.00" departLane="28557537#1_0" departPos="5.10" departSpeed="0.00" departDelay="0.00" arrival="25547.00" arrivalLane="-22873531#1_0" arrivalPos="92.66" arrivalSpeed="12.61" duration="100.00" routeLength="1629.58" waitSteps="0" rerouteNo="1" devices="tripinfo_143559_143559_415 routing_143559_143559_415" vType="DEFAULT_VEHTYPE" vaporized=""/>
    <tripinfo id="157762_157762_421" depart="25497.00" departLane="28557537#1_0" departPos="5.10" departSpeed="0.00" departDelay="0.00" arrival="25550.00" arrivalLane="-27602630#1_0" arrivalPos="125.61" arrivalSpeed="23.31" duration="53.00" routeLength="1025.72" waitSteps="0" rerouteNo="1" devices="tripinfo_157762_157762_421 routing_157762_157762_421" vType="DEFAULT_VEHTYPE" vaporized=""/>
    <tripinfo id="155258_155258_420" depart="25477.00" departLane="31694310#0_0" departPos="5.10" departSpeed="0.00" departDelay="0.00" arrival="25553.00" arrivalLane="37866521#1_0" arrivalPos="52.00" arrivalSpeed="13.41" duration="76.00" routeLength="1026.54" waitSteps="0" rerouteNo="1" devices="tripinfo_155258_155258_420 routing_155258_155258_420" vType="DEFAULT_VEHTYPE" vaporized=""/>
    <tripinfo id="158769_158769_421" depart="25440.00" departLane="154755085#0_0" departPos="5.10" departSpeed="0.00" departDelay="0.00" arrival="25561.00" arrivalLane="24234277#0_0" arrivalPos="111.50" arrivalSpeed="12.79" duration="121.00" routeLength="1149.63" waitSteps="0" rerouteNo="1" devices="tripinfo_158769_158769_421 routing_158769_158769_421" vType="DEFAULT_VEHTYPE" vaporized=""/>
    <tripinfo id="124922_124922_406" depart="25434.00" departLane="151057637#2_0" departPos="5.10" departSpeed="0.00" departDelay="0.00" arrival="25578.00" arrivalLane="23015529#0_0" arrivalPos="184.87" arrivalSpeed="13.03" duration="144.00" routeLength="1971.35" waitSteps="0" rerouteNo="1" devices="tripinfo_124922_124922_406 routing_124922_124922_406" vType="DEFAULT_VEHTYPE" vaporized=""/>
    <tripinfo id="133956_133956_411" depart="25560.00" departLane="164158185#1_0" departPos="5.10" departSpeed="0.00" departDelay="0.00" arrival="25579.00" arrivalLane="164158185#1_0" arrivalPos="208.62" arrivalSpeed="13.08" duration="19.00" routeLength="203.52" waitSteps="0" rerouteNo="1" devices="tripinfo_133956_133956_411 routing_133956_133956_411" vType="DEFAULT_VEHTYPE" vaporized=""/>
    <tripinfo id="162726_162726_422" depart="25470.00" departLane="151057637#2_0" departPos="5.10" departSpeed="0.00" departDelay="0.00" arrival="25584.00" arrivalLane="150039002#2_1" arrivalPos="261.12" arrivalSpeed="12.78" duration="114.00" routeLength="1078.70" waitSteps="25" rerouteNo="1" devices="tripinfo_162726_162726_422 routing_162726_162726_422" vType="DEFAULT_VEHTYPE" vaporized=""/>
    <tripinfo id="173801_173801_427" depart="25485.00" departLane="37331980#0_0" departPos="5.10" departSpeed="0.00" departDelay="0.00" arrival="25593.00" arrivalLane="130659365_0" arrivalPos="223.21" arrivalSpeed="13.01" duration="108.00" routeLength="1226.13" waitSteps="0" rerouteNo="1" devices="tripinfo_173801_173801_427 routing_173801_173801_427" vType="DEFAULT_VEHTYPE" vaporized=""/>
    <tripinfo id="150458_150458_418" depart="25521.00" departLane="28557537#1_0" departPos="5.10" departSpeed="0.00" departDelay="0.00" arrival="25607.00" arrivalLane="23493260#7_1" arrivalPos="59.96" arrivalSpeed="12.67" duration="86.00" routeLength="1455.60" waitSteps="0" rerouteNo="1" devices="tripinfo_150458_150458_418 routing_150458_150458_418" vType="DEFAULT_VEHTYPE" vaporized=""/>
    <tripinfo id="140621_140621_414" depart="25573.00" departLane="94096720#1_0" departPos="5.10" departSpeed="0.00" departDelay="0.00" arrival="25613.00" arrivalLane="210039165#1_0" arrivalPos="131.99" arrivalSpeed="13.31" duration="40.00" routeLength="227.63" waitSteps="11" rerouteNo="1" devices="tripinfo_140621_140621_414 routing_140621_140621_414" vType="DEFAULT_VEHTYPE" vaporized=""/>
    <tripinfo id="175084_175084_428" depart="25567.00" departLane="37331980#0_0" departPos="5.10" departSpeed="0.00" departDelay="0.00" arrival="25640.00" arrivalLane="23471158#9_0" arrivalPos="213.75" arrivalSpeed="27.55" duration="73.00" routeLength="952.35" waitSteps="0" rerouteNo="1" devices="tripinfo_175084_175084_428 routing_175084_175084_428" vType="DEFAULT_VEHTYPE" vaporized=""/>
    <tripinfo id="159374_159374_421" depart="25589.00" departLane="151057637#2_0" departPos="5.10" departSpeed="0.00" departDelay="0.00" arrival="25645.00" arrivalLane="23471158#9_0" arrivalPos="213.75" arrivalSpeed="27.65" duration="56.00" routeLength="917.61" waitSteps="1" rerouteNo="1" devices="tripinfo_159374_159374_421 routing_159374_159374_421" vType="DEFAULT_VEHTYPE" vaporized=""/>
    <tripinfo id="156704_156704_421" depart="25532.00" departLane="4380937#0_0" departPos="5.10" departSpeed="0.00" departDelay="0.00" arrival="25647.00" arrivalLane="37866521#1_0" arrivalPos="52.00" arrivalSpeed="12.86" duration="115.00" routeLength="1366.73" waitSteps="0" rerouteNo="1" devices="tripinfo_156704_156704_421 routing_156704_156704_421" vType="DEFAULT_VEHTYPE" vaporized=""/>
    <tripinfo id="166529_166529_424" depart="25581.00" departLane="37331980#0_0" departPos="5.10" departSpeed="0.00" departDelay="0.00" arrival="25651.00" arrivalLane="23471158#9_0" arrivalPos="213.75" arrivalSpeed="27.73" duration="70.00" routeLength="952.35" waitSteps="0" rerouteNo="1" devices="tripinfo_166529_166529_424 routing_166529_166529_424" vType="DEFAULT_VEHTYPE" vaporized=""/>
    <tripinfo id="160100_160100_421" depart="25553.00" departLane="151057637#2_0" departPos="5.10" departSpeed="0.00" departDelay="0.00" arrival="25665.00" arrivalLane="23471158#0_0" arrivalPos="199.81" arrivalSpeed="27.63" duration="112.00" routeLength="1104.84" waitSteps="22" rerouteNo="1" devices="tripinfo_160100_160100_421 routing_160100_160100_421" vType="DEFAULT_VEHTYPE" vaporized=""/>
    <tripinfo id="165861_165861_424" depart="25604.00" departLane="-200671461_0" departPos="5.10" departSpeed="0.00" departDelay="0.00" arrival="25674.00" arrivalLane="-8225144#3_0" arrivalPos="129.39" arrivalSpeed="12.77" duration="70.00" routeLength="677.62" waitSteps="0" rerouteNo="1" devices="tripinfo_165861_165861_424 routing_165861_165861_424" vType="DEFAULT_VEHTYPE" vaporized=""/>
    <tripinfo id="147158_147158_416" depart="25638.00" departLane="31694310#0_0" departPos="5.10" departSpeed="0.00" departDelay="0.00" arrival="25678.00" arrivalLane="8225128#0_0" arrivalPos="152.72" arrivalSpeed="12.75" duration="40.00" routeLength="516.16" waitSteps="0" rerouteNo="1" devices="tripinfo_147158_147158_416 routing_147158_147158_416" vType="DEFAULT_VEHTYPE" vaporized=""/>
    <tripinfo id="145405_145405_416" depart="25669.00" departLane="164158185#1_0" departPos="5.10" departSpeed="0.00" departDelay="0.00" arrival="25687.00" arrivalLane="164158185#1_0" arrivalPos="208.62" arrivalSpeed="12.64" duration="18.00" routeLength="203.52" waitSteps="0" rerouteNo="1" devices="tripinfo_145405_145405_416 routing_145405_145405_416" vType="DEFAULT_VEHTYPE" vaporized=""/>
    <tripinfo id="140615_140615_414" depart="25629.00" departLane="32064260#0_0" departPos="5.10" departSpeed="0.00" departDelay="0.00" arrival="25692.00" arrivalLane="32064260#3_0" arrivalPos="126.56" arrivalSpeed="13.43" duration="63.00" routeLength="211.00" waitSteps="36" rerouteNo="1" devices="tripinfo_140615_140615_414 routing_140615_140615_414" vType="DEFAULT_VEHTYPE" vaporized=""/>
    <tripinfo id="150617_150617_418" depart="25688.00" departLane="-175607927#0_0" departPos="5.10" departSpeed="0.00" departDelay="0.00" arrival="25718.00" arrivalLane="4400305_1" arrivalPos="163.40" arrivalSpeed="13.24" duration="30.00" routeLength="301.08" waitSteps="0" rerouteNo="1" devices="tripinfo_150617_150617_418 routing_150617_150617_418" vType="DEFAULT_VEHTYPE" vaporized=""/>
    <tripinfo id="171414_171414_426" depart="25657.00" departLane="28557537#1_0" departPos="5.10" departSpeed="0.00" departDelay="0.00" arrival="25723.00" arrivalLane="145575263_1" arrivalPos="260.32" arrivalSpeed="13.85" duration="66.00" routeLength="911.63" waitSteps="0" rerouteNo="1" devices="tripinfo_171414_171414_426 routing_171414_171414_426" vType="DEFAULT_VEHTYPE" vaporized=""/>
    <tripinfo id="163499_163499_422" depart="25595.00" departLane="28557537#1_0" departPos="5.10" departSpeed="0.00" departDelay="0.00" arrival="25731.00" arrivalLane="4353628#0_0" arrivalPos="124.71" arrivalSpeed="13.60" duration="136.00" routeLength="1166.12" waitSteps="56" rerouteNo="1" devices="tripinfo_163499_163499_422 routing_163499_163499_422" vType="DEFAULT_VEHTYPE" vaporized=""/>
    <tripinfo id="160002_160002_421" depart="25663.00" departLane="37331980#0_0" departPos="5.10" departSpeed="0.00" departDelay="0.00" arrival="25734.00" arrivalLane="23471158#9_0" arrivalPos="213.75" arrivalSpeed="27.50" duration="71.00" routeLength="952.35" waitSteps="0" rerouteNo="1" devices="tripinfo_160002_160002_421 routing_160002_160002_421" vType="DEFAULT_VEHTYPE" vaporized=""/>
    <tripinfo id="160392_160392_421" depart="25648.00" departLane="37331980#0_0" departPos="5.10" departSpeed="0.00" departDelay="0.00" arrival="25736.00" arrivalLane="36590979#0_0" arrivalPos="136.60" arrivalSpeed="22.12" duration="88.00" routeLength="1048.53" waitSteps="0" rerouteNo="1" devices="tripinfo_160392_160392_421 routing_160392_160392_421" vType="DEFAULT_VEHTYPE" vaporized=""/>
    <tripinfo id="154083_154083_420" depart="25711.00" departLane="-175607927#0_0" departPos="5.10" departSpeed="0.00" departDelay="0.00" arrival="25741.00" arrivalLane="-29214406_0" arrivalPos="179.38" arrivalSpeed="13.29" duration="30.00" routeLength="317.06" waitSteps="0" rerouteNo="1" devices="tripinfo_154083_154083_420 routing_154083_154083_420" vType="DEFAULT_VEHTYPE" vaporized=""/>
    <tripinfo id="156311_156311_420" depart="25543.00" departLane="151057637#2_0" departPos="5.10" departSpeed="0.00" departDelay="0.00" arrival="25765.00" arrivalLane="85470309#4_0" arrivalPos="208.83" arrivalSpeed="13.49" duration="222.00" routeLength="1931.88" waitSteps="69" rerouteNo="1" devices="tripinfo_156311_156311_420 routing_156311_156311_420" vType="DEFAULT_VEHTYPE" vaporized=""/>
    <tripinfo id="172259_172259_426" depart="25682.00" departLane="28557537#1_0" departPos="5.10" departSpeed="0.00" departDelay="0.00" arrival="25767.00" arrivalLane="23493260#7_1" arrivalPos="59.96" arrivalSpeed="12.60" duration="85.00" routeLength="1455.60" waitSteps="0" rerouteNo="1" devices="tripinfo_172259_172259_426 routing_172259_172259_426" vType="DEFAULT_VEHTYPE" vaporized=""/>
    <tripinfo id="129454_129454_408" depart="25678.00" departLane="110967367#0_0" departPos="5.10" departSpeed="0.00" departDelay="0.00" arrival="25767.00" arrivalLane="4400203#0_0" arrivalPos="78.07" arrivalSpeed="7.59" duration="89.00" routeLength="306.58" waitSteps="48" rerouteNo="1" devices="tripinfo_129454_129454_408 routing_129454_129454_408" vType="DEFAULT_VEHTYPE" vaporized=""/>
    <tripinfo id="159698_159698_421" depart="25757.00" departLane="-32064260#4_0" departPos="5.10" departSpeed="0.00" departDelay="0.00" arrival="25776.00" arrivalLane="-32064260#1_0" arrivalPos="89.54" arrivalSpeed="13.03" duration="19.00" routeLength="211.00" waitSteps="0" rerouteNo="1" devices="tripinfo_159698_159698_421 routing_159698_159698_421" vType="DEFAULT_VEHTYPE" vaporized=""/>
    <tripinfo id="161774_161774_421" depart="25695.00" departLane="151057637#2_0" departPos="5.10" departSpeed="0.00" departDelay="0.00" arrival="25776.00" arrivalLane="3065455_0" arrivalPos="55.65" arrivalSpeed="13.71" duration="81.00" routeLength="669.49" waitSteps="0" rerouteNo="1" devices="tripinfo_161774_161774_421 routing_161774_161774_421" vType="DEFAULT_VEHTYPE" vaporized=""/>
    <tripinfo id="174530_174530_427" depart="25621.00" departLane="4401673#6_0" departPos="5.10" departSpeed="0.00" departDelay="0.00" arrival="25777.00" arrivalLane="23799989#0_0" arrivalPos="128.40" arrivalSpeed="7.97" duration="156.00" routeLength="1722.67" waitSteps="2" rerouteNo="1" devices="tripinfo_174530_174530_427 routing_174530_174530_427" vType="DEFAULT_VEHTYPE" vaporized=""/>
    <tripinfo id="156930_156930_421" depart="25725.00" departLane="8225144#1_0" departPos="5.10" departSpeed="0.00" departDelay="0.00" arrival="25778.00" arrivalLane="200671461_0" arrivalPos="64.70" arrivalSpeed="13.44" duration="53.00" routeLength="542.57" waitSteps="0" rerouteNo="1" devices="tripinfo_156930_156930_421 routing_156930_156930_421" vType="DEFAULT_VEHTYPE" vaporized=""/>
    <tripinfo id="149734_149734_417" depart="25615.00" departLane="37331980#0_0" departPos="5.10" departSpeed="0.00" departDelay="0.00" arrival="25789.00" arrivalLane="2837877_0" arrivalPos="210.13" arrivalSpeed="7.46" duration="174.00" routeLength="1294.71" waitSteps="25" rerouteNo="1" devices="tripinfo_149734_149734_417 routing_149734_149734_417" vType="DEFAULT_VEHTYPE" vaporized=""/>
    <tripinfo id="179572_179572_430" depart="25744.00" departLane="-37866521#1_0" departPos="5.10" departSpeed="0.00" departDelay="0.00" arrival="25798.00" arrivalLane="-8225144#3_0" arrivalPos="129.39" arrivalSpeed="13.43" duration="54.00" routeLength="572.26" waitSteps="0" rerouteNo="1" devices="tripinfo_179572_179572_430 routing_179572_179572_430" vType="DEFAULT_VEHTYPE" vaporized=""/>
    <tripinfo id="179592_179592_430" depart="25716.00" departLane="28557537#1_0" departPos="5.10" departSpeed="0.00" departDelay="0.00" arrival="25802.00" arrivalLane="23493260#7_1" arrivalPos="59.96" arrivalSpeed="12.97" duration="86.00" routeLength="1455.60" waitSteps="0" rerouteNo="1" devices="tripinfo_179592_179592_430 routing_179592_179592_430" vType="DEFAULT_VEHTYPE" vaporized=""/>
    <tripinfo id="186664_186664_432" depart="25768.00" departLane="4400305_0" departPos="5.10" departSpeed="0.00" departDelay="0.00" arrival="25811.00" arrivalLane="33469672_0" arrivalPos="142.78" arrivalSpeed="13.78" duration="43.00" routeLength="450.72" waitSteps="0" rerouteNo="1" devices="tripinfo_186664_186664_432 routing_186664_186664_432" vType="DEFAULT_VEHTYPE" vaporized=""/>
    <tripinfo id="184927_184927_431" depart="25780.00" departLane="32064260#0_0" departPos="5.10" departSpeed="0.00" departDelay="0.00" arrival="25812.00" arrivalLane="4390557#1_0" arrivalPos="163.47" arrivalSpeed="7.31" duration="32.00" routeLength="247.91" waitSteps="0" rerouteNo="1" devices="tripinfo_184927_184927_431 routing_184927_184927_431" vType="DEFAULT_VEHTYPE" vaporized=""/>
    <tripinfo id="184200_184200_431" depart="25805.00" departLane="24900427#2_0" departPos="5.10" departSpeed="0.00" departDelay="0.00" arrival="25821.00" arrivalLane="8225124#1_0" arrivalPos="86.14" arrivalSpeed="13.65" duration="16.00" routeLength="178.96" waitSteps="0" rerouteNo="1" devices="tripinfo_184200_184200_431 routing_184200_184200_431" vType="DEFAULT_VEHTYPE" vaporized=""/>
    <tripinfo id="145779_145779_416" depart="25797.00" departLane="4400306#0_0" departPos="5.10" departSpeed="0.00" departDelay="0.00" arrival="25835.00" arrivalLane="40236119_0" arrivalPos="102.15" arrivalSpeed="13.52" duration="38.00" routeLength="326.62" waitSteps="0" rerouteNo="1" devices="tripinfo_145779_145779_416 routing_145779_145779_416" vType="DEFAULT_VEHTYPE" vaporized=""/>
    <tripinfo id="170650_170650_426" depart="25734.00" departLane="154755085#0_0" departPos="5.10" departSpeed="0.00" departDelay="0.00" arrival="25848.00" arrivalLane="23471158#9_0" arrivalPos="213.75" arrivalSpeed="27.46" duration="114.00" routeLength="1551.20" waitSteps="0" rerouteNo="1" devices="tripinfo_170650_170650_426 routing_170650_170650_426" vType="DEFAULT_VEHTYPE" vaporized=""/>
    <tripinfo id="178712_178712_430" depart="25763.00" departLane="31694310#0_0" departPos="5.10" departSpeed="0.00" departDelay="0.00" arrival="25862.00" arrivalLane="23493260#7_0" arrivalPos="59.96" arrivalSpeed="13.72" duration="99.00" routeLength="1181.88" waitSteps="0" rerouteNo="1" devices="tripinfo_178712_178712_430 routing_178712_178712_430" vType="DEFAULT_VEHTYPE" vaporized=""/>
    <tripinfo id="175364_175364_428" depart="25788.00" departLane="37331980#0_0" departPos="5.10" departSpeed="0.00" departDelay="0.00" arrival="25877.00" arrivalLane="23471158#9_0" arrivalPos="213.75" arrivalSpeed="27.55" duration="89.00" routeLength="952.35" waitSteps="12" rerouteNo="1" devices="tripinfo_175364_175364_428 routing_175364_175364_428" vType="DEFAULT_VEHTYPE" vaporized=""/>
    <tripinfo id="173845_173845_427" depart="25816.00" departLane="8225102_0" departPos="5.10" departSpeed="0.00" departDelay="0.00" arrival="25904.00" arrivalLane="23493260#7_0" arrivalPos="59.96" arrivalSpeed="12.83" duration="88.00" routeLength="777.90" waitSteps="0" rerouteNo="1" devices="tripinfo_173845_173845_427 routing_173845_173845_427" vType="DEFAULT_VEHTYPE" vaporized=""/>
    <tripinfo id="189900_189900_434" depart="25826.00" departLane="154755085#0_0" departPos="5.10" departSpeed="0.00" departDelay="0.00" arrival="25915.00" arrivalLane="4400295#0_0" arrivalPos="146.71" arrivalSpeed="12.84" duration="89.00" routeLength="885.87" waitSteps="0" rerouteNo="1" devices="tripinfo_189900_189900_434 routing_189900_189900_434" vType="DEFAULT_VEHTYPE" vaporized=""/>
    <tripinfo id="153806_153806_420" depart="25791.00" departLane="-200671461_0" departPos="5.10" departSpeed="0.00" departDelay="0.00" arrival="25922.00" arrivalLane="23471158#9_0" arrivalPos="213.75" arrivalSpeed="27.65" duration="131.00" routeLength="1886.55" waitSteps="0" rerouteNo="1" devices="tripinfo_153806_153806_420 routing_153806_153806_420" vType="DEFAULT_VEHTYPE" vaporized=""/>
    <tripinfo id="181426_181426_431" depart="25842.00" departLane="28557537#1_0" departPos="5.10" departSpeed="0.00" departDelay="0.00" arrival="25928.00" arrivalLane="23493260#7_1" arrivalPos="59.96" arrivalSpeed="13.59" duration="86.00" routeLength="1455.60" waitSteps="0" rerouteNo="1" devices="tripinfo_181426_181426_431 routing_181426_181426_431" vType="DEFAULT_VEHTYPE" vaporized=""/>
    <tripinfo id="181090_181090_431" depart="25831.00" departLane="150031221_0" departPos="5.10" departSpeed="0.00" departDelay="0.00" arrival="25937.00" arrivalLane="23471158#9_0" arrivalPos="213.75" arrivalSpeed="27.44" duration="106.00" routeLength="1037.08" waitSteps="0" rerouteNo="1" devices="tripinfo_181090_181090_431 routing_181090_181090_431" vType="DEFAULT_VEHTYPE" vaporized=""/>
    <tripinfo id="142735_142735_415" depart="25932.00" departLane="4400306#0_0" departPos="5.10" departSpeed="0.00" departDelay="0.00" arrival="25958.00" arrivalLane="4400306#0_0" arrivalPos="186.84" arrivalSpeed="7.30" duration="26.00" routeLength="181.74" waitSteps="0" rerouteNo="1" devices="tripinfo_142735_142735_415 routing_142735_142735_415" vType="DEFAULT_VEHTYPE" vaporized=""/>
    <tripinfo id="159542_159542_421" depart="25849.00" departLane="37331980#0_0" departPos="5.10" departSpeed="0.00" departDelay="0.00" arrival="25958.00" arrivalLane="23471158#9_0" arrivalPos="213.75" arrivalSpeed="26.67" duration="109.00" routeLength="952.35" waitSteps="31" rerouteNo="1" devices="tripinfo_159542_159542_421 routing_159542_159542_421" vType="DEFAULT_VEHTYPE" vaporized=""/>
    <tripinfo id="171074_171074_426" depart="25871.00" departLane="-200671461_0" departPos="5.10" departSpeed="0.00" departDelay="0.00" arrival="25966.00" arrivalLane="26519352#0_0" arrivalPos="184.56" arrivalSpeed="26.63" duration="95.00" routeLength="1040.24" waitSteps="0" rerouteNo="1" devices="tripinfo_171074_171074_426 routing_171074_171074_426" vType="DEFAULT_VEHTYPE" vaporized=""/>
    <tripinfo id="178542_178542_430" depart="25895.00" departLane="37331980#0_0" departPos="5.10" departSpeed="0.00" departDelay="0.00" arrival="25966.00" arrivalLane="23471158#9_0" arrivalPos="213.75" arrivalSpeed="27.02" duration="71.00" routeLength="952.35" waitSteps="0" rerouteNo="1" devices="tripinfo_178542_178542_430 routing_178542_178542_430" vType="DEFAULT_VEHTYPE" vaporized=""/>
    <tripinfo id="141230_141230_415" depart="25861.00" departLane="154755085#0_0" departPos="5.10" departSpeed="0.00" departDelay="0.00" arrival="25970.00" arrivalLane="154755088#0_0" arrivalPos="201.54" arrivalSpeed="13.14" duration="109.00" routeLength="1073.44" waitSteps="0" rerouteNo="1" devices="tripinfo_141230_141230_415 routing_141230_141230_415" vType="DEFAULT_VEHTYPE" vaporized=""/>
    <tripinfo id="175272_175272_428" depart="25879.00" departLane="31694310#0_0" departPos="5.10" departSpeed="0.00" departDelay="0.00" arrival="25976.00" arrivalLane="23493260#7_0" arrivalPos="59.96" arrivalSpeed="12.75" duration="97.00" routeLength="1181.88" waitSteps="0" rerouteNo="1" devices="tripinfo_175272_175272_428 routing_175272_175272_428" vType="DEFAULT_VEHTYPE" vaporized=""/>
    <tripinfo id="192305_192305_435" depart="25911.00" departLane="154755085#0_0" departPos="5.10" departSpeed="0.00" departDelay="0.00" arrival="25976.00" arrivalLane="154755115#0_1" arrivalPos="53.05" arrivalSpeed="7.76" duration="65.00" routeLength="576.58" waitSteps="0" rerouteNo="1" devices="tripinfo_192305_192305_435 routing_192305_192305_435" vType="DEFAULT_VEHTYPE" vaporized=""/>
    <tripinfo id="151659_151659_419" depart="25889.00" departLane="-200671461_0" departPos="5.10" departSpeed="0.00" departDelay="0.00" arrival="25984.00" arrivalLane="26519352#0_0" arrivalPos="184.56" arrivalSpeed="27.71" duration="95.00" routeLength="1040.24" waitSteps="0" rerouteNo="1" devices="tripinfo_151659_151659_419 routing_151659_151659_419" vType="DEFAULT_VEHTYPE" vaporized=""/>
    <tripinfo id="165425_165425_423" depart="25955.00" departLane="154755085#0_0" departPos="5.10" departSpeed="0.00" departDelay="0.00" arrival="25996.00" arrivalLane="4400311#0_0" arrivalPos="280.07" arrivalSpeed="7.91" duration="41.00" routeLength="299.36" waitSteps="0" rerouteNo="1" devices="tripinfo_165425_165425_423 routing_165425_165425_423" vType="DEFAULT_VEHTYPE" vaporized=""/>
    <tripinfo id="194444_194444_436" depart="26003.00" departLane="32064260#0_0" departPos="5.10" departSpeed="0.00" departDelay="0.00" arrival="26022.00" arrivalLane="32064260#3_0" arrivalPos="126.56" arrivalSpeed="13.36" duration="19.00" routeLength="211.00" waitSteps="0" rerouteNo="1" devices="tripinfo_194444_194444_436 routing_194444_194444_436" vType="DEFAULT_VEHTYPE" vaporized=""/>
    <tripinfo id="179722_179722_430" depart="25940.00" departLane="154755085#0_0" departPos="5.10" departSpeed="0.00" departDelay="0.00" arrival="26023.00" arrivalLane="23493179_1" arrivalPos="112.63" arrivalSpeed="13.25" duration="83.00" routeLength="756.38" waitSteps="0" rerouteNo="1" devices="tripinfo_179722_179722_430 routing_179722_179722_430" vType="DEFAULT_VEHTYPE" vaporized=""/>
    <tripinfo id="168787_168787_425" depart="25922.00" departLane="165515969#0_0" departPos="5.10" departSpeed="0.00" departDelay="0.00" arrival="26030.00" arrivalLane="23493260#7_0" arrivalPos="59.96" arrivalSpeed="13.19" duration="108.00" routeLength="1272.25" waitSteps="0" rerouteNo="1" devices="tripinfo_168787_168787_425 routing_168787_168787_425" vType="DEFAULT_VEHTYPE" vaporized=""/>
    <tripinfo id="199577_199577_437" depart="25983.00" departLane="8225127_0" departPos="5.10" departSpeed="0.00" departDelay="0.00" arrival="26031.00" arrivalLane="85470309#4_0" arrivalPos="208.83" arrivalSpeed="12.95" duration="48.00" routeLength="561.05" waitSteps="0" rerouteNo="1" devices="tripinfo_199577_199577_437 routing_199577_199577_437" vType="DEFAULT_VEHTYPE" vaporized=""/>
    <tripinfo id="177188_177188_429" depart="25948.00" departLane="-37866521#1_0" departPos="5.10" departSpeed="0.00" departDelay="0.00" arrival="26034.00" arrivalLane="8142293#3_0" arrivalPos="142.66" arrivalSpeed="13.09" duration="86.00" routeLength="910.66" waitSteps="0" rerouteNo="1" devices="tripinfo_177188_177188_429 routing_177188_177188_429" vType="DEFAULT_VEHTYPE" vaporized=""/>
    <tripinfo id="202346_202346_438" depart="25975.00" departLane="-29206900_0" departPos="5.10" departSpeed="0.00" departDelay="0.00" arrival="26038.00" arrivalLane="177147101#3_0" arrivalPos="50.48" arrivalSpeed="8.23" duration="63.00" routeLength="447.07" waitSteps="0" rerouteNo="1" devices="tripinfo_202346_202346_438 routing_202346_202346_438" vType="DEFAULT_VEHTYPE" vaporized=""/>
    <tripinfo id="180134_180134_430" depart="25967.00" departLane="154755085#0_0" departPos="5.10" departSpeed="0.00" departDelay="0.00" arrival="26044.00" arrivalLane="29206900_0" arrivalPos="79.62" arrivalSpeed="7.18" duration="77.00" routeLength="671.99" waitSteps="0" rerouteNo="1" devices="tripinfo_180134_180134_430 routing_180134_180134_430" vType="DEFAULT_VEHTYPE" vaporized=""/>
    <tripinfo id="185019_185019_431" depart="26022.00" departLane="-69366482#2_0" departPos="5.10" departSpeed="0.00" departDelay="0.00" arrival="26061.00" arrivalLane="37866521#1_0" arrivalPos="52.00" arrivalSpeed="13.75" duration="39.00" routeLength="401.29" waitSteps="0" rerouteNo="1" devices="tripinfo_185019_185019_431 routing_185019_185019_431" vType="DEFAULT_VEHTYPE" vaporized=""/>
    <tripinfo id="157774_157774_421" depart="26039.00" departLane="-175607927#0_0" departPos="5.10" departSpeed="0.00" departDelay="0.00" arrival="26068.00" arrivalLane="-29214406_0" arrivalPos="179.38" arrivalSpeed="12.78" duration="29.00" routeLength="317.06" waitSteps="0" rerouteNo="1" devices="tripinfo_157774_157774_421 routing_157774_157774_421" vType="DEFAULT_VEHTYPE" vaporized=""/>
    <tripinfo id="149772_149772_417" depart="26049.00" departLane="32064260#0_0" departPos="5.10" departSpeed="0.00" departDelay="0.00" arrival="26092.00" arrivalLane="32064260#3_0" arrivalPos="126.56" arrivalSpeed="13.71" duration="43.00" routeLength="211.00" waitSteps="17" rerouteNo="1" devices="tripinfo_149772_149772_417 routing_149772_149772_417" vType="DEFAULT_VEHTYPE" vaporized=""/>
</tripinfos>
